{
    "id": "customtree:mage_holy_main_1",
    "bonuses": [
        {
            "type": "skilltree:attribute",
            "attribute": "irons_spellbooks:holy_spell_power",
            "id": "f8760722-4f11-47fc-bea3-64281ce9b0fa",
            "name": "Lesser holy 1",
            "amount": 0.02,
            "operation": 0
        }
    ],
    "requirements": [],
    "directConnections": [
        "customtree:mage_holy_main_2"
    ],
    "longConnections": [],
    "oneWayConnections": [],
    "tags": [],
    "backgroundTexture": "skilltree:textures/icons/background/lesser.png",
    "iconTexture": "skilltree:textures/icons/arrow_bronze.png",
    "borderTexture": "skilltree:textures/tooltip/lesser.png",
    "positionX": 292.52,
    "positionY": 34.07,
    "buttonSize": 16,
    "isStartingPoint": false
}