{
    "id": "customtree:mage_fire_subc_3",
    "bonuses": [
        {
            "type": "skilltree:attribute",
            "attribute": "irons_spellbooks:fire_magic_resist",
            "id": "53066419-e5dc-4d5f-9b9c-a59cffd26b7c",
            "name": "Lesser Resist fire subC 3",
            "amount": 0.02,
            "operation": 0
        }
    ],
    "requirements": [],
    "directConnections": [
        "customtree:mage_fire_subc_4"
    ],
    "longConnections": [],
    "oneWayConnections": [],
    "tags": [],
    "backgroundTexture": "skilltree:textures/icons/background/lesser.png",
    "iconTexture": "skilltree:textures/icons/arrow_bronze.png",
    "borderTexture": "skilltree:textures/tooltip/lesser.png",
    "positionX": -157.01,
    "positionY": 500.24,
    "buttonSize": 16,
    "isStartingPoint": false
}