{
    "id": "customtree:mage_ice_subc_4",
    "bonuses": [
        {
            "type": "skilltree:attribute",
            "attribute": "irons_spellbooks:ice_magic_resist",
            "id": "a7b787d6-2496-49cf-81e3-5d36873a6850",
            "name": "Lesser Resist ice subC 4",
            "amount": 0.02,
            "operation": 0
        }
    ],
    "requirements": [],
    "directConnections": [
        "customtree:mage_ice_subc_5"
    ],
    "longConnections": [],
    "oneWayConnections": [],
    "tags": [],
    "backgroundTexture": "skilltree:textures/icons/background/lesser.png",
    "iconTexture": "skilltree:textures/icons/arrow_bronze.png",
    "borderTexture": "skilltree:textures/tooltip/lesser.png",
    "positionX": -221.55,
    "positionY": -548.01,
    "buttonSize": 16,
    "isStartingPoint": false
}