{
    "id": "customtree:mage_lightning_main_13",
    "bonuses": [
        {
            "type": "skilltree:attribute",
            "attribute": "irons_spellbooks:lightning_spell_power",
            "id": "58158c51-1219-4255-8087-ebb6295cfd80",
            "name": "Lesser lightning 13",
            "amount": 0.02,
            "operation": 0
        }
    ],
    "requirements": [],
    "directConnections": [
        "customtree:mage_lightning_main_14"
    ],
    "longConnections": [],
    "oneWayConnections": [],
    "tags": [],
    "backgroundTexture": "skilltree:textures/icons/background/lesser.png",
    "iconTexture": "skilltree:textures/icons/arrow_bronze.png",
    "borderTexture": "skilltree:textures/tooltip/lesser.png",
    "positionX": 126.68,
    "positionY": 482.55,
    "buttonSize": 16,
    "isStartingPoint": false
}