{
    "id": "customtree:mage_ice_suba_5",
    "bonuses": [
        {
            "type": "skilltree:attribute",
            "attribute": "irons_spellbooks:ice_magic_resist",
            "id": "d5a69706-47cd-4059-a6a4-5a0f7d877959",
            "name": "Notable Resist ice subA",
            "amount": 0.1,
            "operation": 1
        }
    ],
    "requirements": [
        {
            "minValue": 2500,
            "statTypeId": "minecraft:custom",
            "statId": "kubejs:mana_spent",
            "type": "skilltree:stat_value"
        }
    ],
    "directConnections": [],
    "longConnections": [],
    "oneWayConnections": [],
    "tags": [],
    "backgroundTexture": "skilltree:textures/icons/background/notable.png",
    "iconTexture": "skilltree:textures/icons/chestplate_fur.png",
    "borderTexture": "skilltree:textures/tooltip/notable.png",
    "positionX": -125.87,
    "positionY": -345.91,
    "buttonSize": 20,
    "isStartingPoint": false
}