{
    "id": "customtree:pk_st1_d",
    "bonuses": [
        {
            "amount": 0.15,
            "attribute": "parcool:stamina_recovery",
            "id": "11111111-0000-0000-0000-000000000024",
            "name": "Lesser Stamina Recovery",
            "operation": 1,
            "player_condition": {
                "type": "skilltree:none"
            },
            "player_multiplier": {
                "type": "skilltree:none"
            },
            "type": "skilltree:attribute"
        }
    ],
    "requirements": [],
    "directConnections": [
        "customtree:pk_0_0",
        "customtree:pk_st2_d"
    ],
    "longConnections": [],
    "oneWayConnections": [],
    "tags": [],
    "backgroundTexture": "skilltree:textures/icons/background/lesser.png",
    "iconTexture": "skilltree:textures/icons/potion_green.png",
    "borderTexture": "skilltree:textures/tooltip/lesser.png",
    "positionX": -38.0,
    "positionY": 14.0,
    "buttonSize": 16,
    "isStartingPoint": false
}