{
  "id": "customtree:pl_r0_cm1",
  "bonuses": [
    {
      "type": "skilltree:attribute",
      "attribute": "irons_spellbooks:max_mana",
      "id": "31e9d6ec-cfe9-4fcd-bcba-8c41a9f15f1e",
      "name": "Max Mana Small",
      "amount": 10.0,
      "operation": 0
    }
  ],
  "requirements": [],
  "directConnections": [
    "customtree:pl_rm1_cm1",
    "customtree:pl_r1_cm1",
    "customtree:pl_r0_cm2"
  ],
  "longConnections": [],
  "oneWayConnections": [],
  "tags": [],
  "backgroundTexture": "skilltree:textures/icons/background/lesser.png",
  "iconTexture": "skilltree:textures/icons/potion_blue.png",
  "borderTexture": "skilltree:textures/tooltip/lesser.png",
  "positionX": -48.0,
  "positionY": 0.0,
  "buttonSize": 16,
  "isStartingPoint": false
}