{
  "id": "customtree:sg_notable_bottom",
  "bonuses": [
    {
      "type": "skilltree:attribute",
      "attribute": "irons_spellbooks:blood_spell_power",
      "id": "30000000-0000-0000-0000-000887393801",
      "name": "BloodPower",
      "amount": 0.2,
      "operation": 1
    }
  ],
  "requirements": [
    {
      "type": "skilltree:stat_value",
      "statTypeId": "minecraft:custom",
      "statId": "minecraft:damage_blocked_by_shield",
      "minValue": 50000
    }
  ],
  "directConnections": [
    "customtree:sg_apex_bottom"
  ],
  "longConnections": [],
  "oneWayConnections": [],
  "tags": [],
  "backgroundTexture": "skilltree:textures/icons/background/notable.png",
  "iconTexture": "skilltree:textures/icons/potion_red.png",
  "borderTexture": "skilltree:textures/tooltip/notable.png",
  "positionX": 0.0,
  "positionY": 400.0,
  "buttonSize": 20,
  "isStartingPoint": false
}